[{"model": "property_managment.propertyimages", "pk": 1, "fields": {"description": "", "image": "assets/images/585203728.jpg", "property": 2}}, {"model": "property_managment.propertyimages", "pk": 2, "fields": {"description": "", "image": "assets/images/585212542.jpg", "property": 2}}, {"model": "property_managment.propertyimages", "pk": 3, "fields": {"description": "", "image": "assets/images/téléchargement.jpeg", "property": 1}}, {"model": "property_managment.propertyimages", "pk": 4, "fields": {"description": "", "image": "assets/images/635414907.jpg", "property": 1}}]